pancollection/PanCollection_colab.ipynb
pancollection/__init__.py
pancollection/run_pansharpening.py
pancollection/run_test_pansharpening.py
pancollection/run_train_model.py
pancollection/common/__init__.py
pancollection/common/builder.py
pancollection/common/dataset.py
pancollection/common/dataset_hp.py
pancollection/common/evaluate.py
pancollection/common/psdata.py
pancollection/common/test_panloader.py
pancollection/common/train_panloader.py
pancollection/common/valid_panloader.py
pancollection/common/FS_index/D_lambda_K.py
pancollection/common/FS_index/HQNR.py
pancollection/common/FS_index/MTF.py
pancollection/common/FS_index/MTF_pan.py
pancollection/common/FS_index/__init__.py
pancollection/common/FS_index/genMTF.py
pancollection/common/FS_index/genMTF_pan.py
pancollection/common/FS_index/imresize.py
pancollection/common/FS_index/indexes_evaluation_FS.py
pancollection/common/FS_index/interp23.py
pancollection/common/FS_index/my_D_s.py
pancollection/common/FS_index/my_q2n.py
pancollection/common/FS_index/tools.py
pancollection/common/tests/__init__.py
pancollection/configs/__init__.py
pancollection/configs/configs.py
pancollection/configs/hook_configs.py
pancollection/configs/load_ckpt_configs.py
pancollection/configs/option_DCFNet.py
pancollection/configs/option_LAGNet.py
pancollection/configs/option_bdpn.py
pancollection/configs/option_dicnn.py
pancollection/configs/option_drpnn.py
pancollection/configs/option_fusionnet.py
pancollection/configs/option_msdcnn.py
pancollection/configs/option_pannet.py
pancollection/configs/option_pnn.py
pancollection/models/__init__.py
pancollection/models/base_model.py
pancollection/models/ADKNet/__init__.py
pancollection/models/ADKNet/ddf/__init__.py
pancollection/models/ADKNet/ddf/ddf.py
pancollection/models/ADKNet/ddf/setup.py
pancollection/models/BDPN/__init__.py
pancollection/models/BDPN/bdpn_main.py
pancollection/models/BDPN/model_bdpn.py
pancollection/models/DCFNet/__init__.py
pancollection-0.3.6.dist-info/LICENSE
pancollection-0.3.6.dist-info/METADATA
pancollection-0.3.6.dist-info/WHEEL
pancollection-0.3.6.dist-info/top_level.txt
pancollection-0.3.6.dist-info/RECORD
