Metadata-Version: 2.1
Name: pancollection
Version: 0.3.6
Summary: PanCollection based on UDL (https://github.com/XiaoXiao-Woo/UDL)
Home-page: https://github.com/XiaoXiao-Woo/PanCollection
Author: XiaoXiao-Woo
Author-email: wxwsx1997@gmail.com
License: GPLv3
Classifier: Programming Language :: Python :: 3
Classifier: License :: OSI Approved :: GNU General Public License v3 (GPLv3)
Classifier: Operating System :: OS Independent
Requires-Python: >=3.7
License-File: LICENSE
Requires-Dist: psutil
Requires-Dist: opencv-python
Requires-Dist: numpy
Requires-Dist: matplotlib
Requires-Dist: tensorboard
Requires-Dist: addict
Requires-Dist: yapf
Requires-Dist: imageio
Requires-Dist: colorlog
Requires-Dist: scipy
Requires-Dist: h5py
Requires-Dist: regex
Requires-Dist: packaging
Requires-Dist: pyyaml
Requires-Dist: udl-vis
